repair.py
PDF_Repair-1.1.data/scripts/repair.py
PDF_Repair-1.1.dist-info/METADATA
PDF_Repair-1.1.dist-info/WHEEL
PDF_Repair-1.1.dist-info/entry_points.txt
PDF_Repair-1.1.dist-info/top_level.txt
PDF_Repair-1.1.dist-info/RECORD
