Metadata-Version: 2.1
Name: PDF-Repair
Version: 1.1
Summary: PDFRepair Tool using PyPDF
Home-page: https://github.com/obtuse-triangle/PDFRepair-PyPDF
Author: obtuse-triangle
Author-email: me@obtuse.kr
Requires-Dist: pypdf
Requires-Dist: tqdm
Requires-Dist: argparse
